certbot_dns_hostker/__init__.py
certbot_dns_hostker/dns_hostker.py
certbot_dns_hostker-0.0.2.dist-info/LICENSE
certbot_dns_hostker-0.0.2.dist-info/METADATA
certbot_dns_hostker-0.0.2.dist-info/WHEEL
certbot_dns_hostker-0.0.2.dist-info/entry_points.txt
certbot_dns_hostker-0.0.2.dist-info/top_level.txt
certbot_dns_hostker-0.0.2.dist-info/RECORD
