Metadata-Version: 2.1
Name: certbot-dns-hostker
Version: 0.0.2
Summary: Certbot for Hostker DNS
Home-page: https://www.codesky.me
Author: SkyAo
Author-email: csvwolf@qq.com
License: UNKNOWN
Platform: UNKNOWN
